cv2/__init__.py
cv2/config-3.py
cv2/config.py
cv2/load_config_py2.py
cv2/load_config_py3.py
cv2/version.py
cv2/data/__init__.py
cv2/gapi/__init__.py
cv2/mat_wrapper/__init__.py
cv2/misc/__init__.py
cv2/misc/version.py
cv2/utils/__init__.py
src/FasterTg.py
src/__init__.py
src/mystarts.py
src/pyfunc.py
src/pyutils.py
src/telefunc.py
src/teleutils.py
package_ethon_setup-0.0.2.dist-info/METADATA
package_ethon_setup-0.0.2.dist-info/WHEEL
package_ethon_setup-0.0.2.dist-info/licenses/LICENSE
package_ethon_setup-0.0.2.dist-info/RECORD
