Metadata-Version: 2.1
Name: Package-Ethon-setup
Version: 0.0.2
Summary: This Package Is Helpfull for Save Restriction Bot
Project-URL: Homepage, https://github.com/rohitsir1999/Package-Ethon
Project-URL: Bug Tracker, https://github.com/rohitsir1999/Package-Ethon/issues
Author-email: Rudraa <rudraa2213@gmail.com>
License-File: LICENSE
Classifier: License :: OSI Approved :: MIT License
Classifier: Operating System :: OS Independent
Classifier: Programming Language :: Python :: 3
Requires-Python: >=3.7
